LICENSE
MANIFEST.in
README
setup.py
examples/__init__.py
examples/test_decorators.py
examples/test_reader.py
examples/test_settings.py
examples/web/__init__.py
examples/web/test_browser.py
pymisc/__init__.py
pymisc/__init__.pyc
pymisc/abstract.py
pymisc/applications.py
pymisc/decorators.py
pymisc/settings.py
pymisc.egg-info/PKG-INFO
pymisc.egg-info/SOURCES.txt
pymisc.egg-info/dependency_links.txt
pymisc.egg-info/requires.txt
pymisc.egg-info/top_level.txt
pymisc/django/__init__.py
pymisc/django/decorators.py
pymisc/django/errors.py
pymisc/django/exceptions.py
pymisc/django/json_encode.py
pymisc/django/middleware.py
pymisc/django/utils.py
pymisc/django/templatetags/__init__.py
pymisc/django/templatetags/bbcode.py
pymisc/django/templatetags/html_tags.py
pymisc/django/templatetags/misc.py
pymisc/django/templatetags/share_buttons.py
pymisc/html/__init__.py
pymisc/html/clear.py
pymisc/html/example.cfg
pymisc/html/generator.py
pymisc/html/needs.cfg
pymisc/reader/__init__.py
pymisc/reader/csvreader.py
pymisc/reader/csvutils.py
pymisc/reader/interfaces.py
pymisc/utils/__init__.py
pymisc/utils/crypt.py
pymisc/utils/date.py
pymisc/utils/distances.py
pymisc/utils/func.py
pymisc/utils/output.py
pymisc/utils/sort.py
pymisc/utils/stat_utils.py
pymisc/utils/structs.py
pymisc/utils/urls.py
pymisc/web/__init__.py
pymisc/web/browser.py