Metadata-Version: 1.0
Name: pymisc
Version: 0.0.2
Summary: Python miscellaneous - module with different useful stuff.
